setup.cfg
setup.py
updown/__init__.py
updown.egg-info/PKG-INFO
updown.egg-info/SOURCES.txt
updown.egg-info/dependency_links.txt
updown.egg-info/requires.txt
updown.egg-info/top_level.txt