Metadata-Version: 1.1
Name: updown
Version: 0.1.0
Summary: 3rd-party Python interface to Updown.io API
Home-page: http://github.com/brandonhamilton/updown-python
Author: Brandon Hamilton
Author-email: brandon.hamilton@gmail.com
License: MIT
Platform: UNKNOWN
Classifier: Development Status :: 3 - Alpha
Classifier: Intended Audience :: Developers
Classifier: Intended Audience :: System Administrators
Classifier: License :: OSI Approved :: MIT License
Classifier: Operating System :: OS Independent
Classifier: Topic :: System :: Monitoring
